{"macroCollection":{"idsInOrderCollection":[],"_collection":[]},"name":"Uciea_vanilla_JIS","selections":{"tab":{"remap":{}},"keyboardKey":{"toDetailCollection":{},"id":"C562CCCC-D99D-4CF4-874A-6356D7F0D29B","fromDetail":{"display":"A","output":{"letter_keys":{"_0":"a"}}}},"macroTab":{"userMacro":{}},"combo":{"key_down_order":"insensitive","id":"AE934B3A-8DCA-4ED1-9EDB-2C661D573E37","key_up_order":"insensitive","comboThreshold":50,"toDetail":{}},"toDetail_macro":{"withModifier":{},"id":"D2AADCA0-DD9D-4E00-8EA0-95A93996B034","outputAndDisplay":{"output":{"letter_keys":{"_0":"a"}},"display":"none","layerKey":"layer0"},"indicator":false,"error":false},"macro":{"name":"user Macro","toDetailCollection":{"idsInOrderCollection":[],"_collection":[]},"id":"D477A08C-AA25-4AFC-93F4-E01891F227DD","dictionary_key":null},"layer":"layer0","fromTab":{"qwertyKeyboard":{}},"condition":"condition0","toTab":"qwertyKeyboard","customOrMacroTab":{"customizeKey":{}}},"keymap":{"validSections":{"sections":[{"main":{}}]},"main":{"isEnableMain":true,"sectionDetail":{"section":{"main":{}},"deviceDetail":{"product_id":"product_id","is_product_id_Enabled":false,"location_id":"location_id","device_name":"mainKeyboard","is_location_id_Enabled":false,"is_builtin_keyboard":false,"is_vendor_id_Enabled":false,"vendor_id":"vendor_id"}},"subRows":{"row5":[{"isSpacer":true,"id":"6230ABCE-E4C7-49CC-A34B-44F13C87040E","toDetailCollection":{},"fromDetail":{"output":{"letter_keys":{"_0":"a"}},"display":"A"}},{"fromDetail":{"display":"arrowtriangle.up.fill","isSFSymbol":true,"output":{"arrow_keys":{"_0":"up_arrow"}}},"toDetailCollection":{},"id":"D81C7FD4-F6EB-44CD-B39E-23A5AE5A4822"}],"row1":[{"toDetailCollection":{},"fromDetail":{"display":"F15","output":{"function_keys":{"_0":"f15"}}},"id":"30238BCD-9475-471F-A73F-E705C4B752FD"},{"id":"6266DB45-87C2-4D9C-92A4-254557CF09A8","fromDetail":{"output":{"function_keys":{"_0":"f14"}},"display":"F14"},"toDetailCollection":{}},{"id":"241296C8-A18A-479A-BA76-093DF29539D3","fromDetail":{"display":"F13","output":{"function_keys":{"_0":"f13"}}},"toDetailCollection":{}}],"rowIndex_arrow":{"row6":{}},"idsInOrderRow3":[{"id":"7190356D-48A0-4A39-8316-C8FEF68252F3"},{"id":"82907F6F-5AF0-4655-9A88-3755E05C39D4"},{"id":"1947117C-57BA-445B-B0E6-2EEEC745EAD5"}],"arrow_up":{"toDetailCollection":{},"fromDetail":{"display":"arrowtriangle.up.fill","isSFSymbol":true,"output":{"arrow_keys":{"_0":"up_arrow"}}},"keyShape":"arrow_Up","id":"CD92E46E-CA55-44DE-8A51-6913C17A749A"},"enableArrowKeys":false,"arrow_down":{"id":"21ACA7D1-143B-4927-80C8-918AEDB16DE2","keyShape":"arrow_Down","toDetailCollection":{},"fromDetail":{"output":{"arrow_keys":{"_0":"down_arrow"}},"isSFSymbol":true,"display":"arrowtriangle.down.fill"}},"arrow_right":{"fromDetail":{"output":{"arrow_keys":{"_0":"right_arrow"}},"display":"arrowtriangle.right.fill","isSFSymbol":true},"id":"AC873864-45C1-4C2E-B2B8-D6361798F633","keyShape":"arrow_LR","toDetailCollection":{}},"idsInOrderRow5":[{"id":"6230ABCE-E4C7-49CC-A34B-44F13C87040E"},{"id":"D81C7FD4-F6EB-44CD-B39E-23A5AE5A4822"}],"row6":[{"toDetailCollection":{},"id":"681FFCAD-82FC-46C5-A696-ABD6460B3418","fromDetail":{"output":{"arrow_keys":{"_0":"right_arrow"}},"display":"arrowtriangle.right.fill","isSFSymbol":true}},{"id":"950F2C19-E2A7-43C1-AD2F-AA3F8F27E818","fromDetail":{"output":{"arrow_keys":{"_0":"down_arrow"}},"display":"arrowtriangle.down.fill","isSFSymbol":true},"toDetailCollection":{}},{"fromDetail":{"isSFSymbol":true,"output":{"arrow_keys":{"_0":"left_arrow"}},"display":"arrowtriangle.left.fill"},"toDetailCollection":{},"id":"EAD097D9-B117-4E49-8BEC-7404470FAF30"}],"idsInOrderRow4":[],"row2":[{"toDetailCollection":{},"fromDetail":{"display":"arrow.up.to.line","isSFSymbol":true,"output":{"arrow_keys":{"_0":"home"}}},"id":"A5BF47D3-F6D2-4E19-9595-BB8E8F524611"},{"toDetailCollection":{},"id":"B796808D-EBBF-4CD9-941E-86475683918B","fromDetail":{"output":{"arrow_keys":{"_0":"page_up"}},"isSFSymbol":true,"display":"arrow.up"}},{"id":"35AB30D1-E468-4649-A1A3-AB022D1C9BB7","toDetailCollection":{},"fromDetail":{"output":{"keys_in_pc_keyboards":{"_0":"insert"}},"isSFSymbol":true,"display":"text.insert"}}],"idsInOrderRow1":[{"id":"241296C8-A18A-479A-BA76-093DF29539D3"},{"id":"6266DB45-87C2-4D9C-92A4-254557CF09A8"},{"id":"30238BCD-9475-471F-A73F-E705C4B752FD"}],"row4":[],"arrow_left":{"fromDetail":{"isSFSymbol":true,"display":"arrowtriangle.left.fill","output":{"arrow_keys":{"_0":"left_arrow"}}},"id":"CA3802B5-961D-43D1-8CEE-B54E21776D4D","keyShape":"arrow_LR","toDetailCollection":{}},"idsInOrderRow2":[{"id":"35AB30D1-E468-4649-A1A3-AB022D1C9BB7"},{"id":"A5BF47D3-F6D2-4E19-9595-BB8E8F524611"},{"id":"B796808D-EBBF-4CD9-941E-86475683918B"}],"row3":[{"toDetailCollection":{},"id":"7190356D-48A0-4A39-8316-C8FEF68252F3","fromDetail":{"display":"delete.right","isSFSymbol":true,"output":{"controls_and_symbols":{"_0":"delete_forward"}}}},{"toDetailCollection":{},"fromDetail":{"isSFSymbol":true,"output":{"arrow_keys":{"_0":"page_down"}},"display":"arrow.down"},"id":"1947117C-57BA-445B-B0E6-2EEEC745EAD5"},{"id":"82907F6F-5AF0-4655-9A88-3755E05C39D4","fromDetail":{"display":"arrow.down.to.line","output":{"arrow_keys":{"_0":"end"}},"isSFSymbol":true},"toDetailCollection":{}}],"idsInOrderRow6":[{"id":"EAD097D9-B117-4E49-8BEC-7404470FAF30"},{"id":"950F2C19-E2A7-43C1-AD2F-AA3F8F27E818"},{"id":"681FFCAD-82FC-46C5-A696-ABD6460B3418"}]},"mainRows":{"enableArrowKeys":true,"arrow_up":{"keyShape":"arrow_Up","id":"598D7EC1-9FCA-4666-9A0C-02AD7F66A042","toDetailCollection":{},"fromDetail":{"output":{"arrow_keys":{"_0":"up_arrow"}},"display":"arrowtriangle.up.fill","isSFSymbol":true}},"idsInOrderRow4":[{"id":"5B37AF98-20A7-441B-B6DC-3D251AA6DA5E"},{"id":"A65A7500-8067-4C58-9D8C-56C0E26B0602"},{"id":"E9E6F415-8585-4BAB-9802-84BCE23E9107"},{"id":"5933351E-9E52-4FFC-960B-4682F54E0E33"},{"id":"CC2EF530-0AAD-46D1-8B0C-6F8F35700942"},{"id":"B293A086-5B36-4647-A7B3-C4BB833B73D1"},{"id":"0F67544B-79C1-4E01-8D33-B358327B5F05"},{"id":"DC19D8B1-9411-4D00-8257-57A0E88B229A"},{"id":"B371E055-8A22-4B90-96A8-7DA77C52AC1D"},{"id":"708E3E6E-FA51-49FB-8E4F-DEC3F8E08FE6"},{"id":"E214B737-667B-4B8A-A49F-A1485BF81C33"},{"id":"0A2EF3A1-02A2-47D1-89E3-5FD639462BE4"},{"id":"6CC29A37-EB0A-4AE6-BB3A-CF98EC6FDC15"}],"row1":[{"id":"3A8E6CAE-163D-4999-9200-CF8534831A27","toDetailCollection":{},"fromDetail":{"output":{"function_keys":{"_0":"f4"}},"display":"F4"}},{"fromDetail":{"display":"F3","output":{"function_keys":{"_0":"f3"}}},"toDetailCollection":{},"id":"D219841C-9444-4BD6-88E3-481251E9F5B0"},{"fromDetail":{"display":"F1","output":{"function_keys":{"_0":"f1"}}},"toDetailCollection":{},"id":"4F3C2609-8EB1-4663-8690-A8639A375AEA"},{"toDetailCollection":{},"id":"A27B70DD-499D-4A45-A249-30A98821F6BB","fromDetail":{"display":"F10","output":{"function_keys":{"_0":"f10"}}}},{"toDetailCollection":{},"fromDetail":{"display":"F7","output":{"function_keys":{"_0":"f7"}}},"id":"1253EBB3-3856-4834-A662-D832BEE5F19C"},{"fromDetail":{"display":"F11","output":{"function_keys":{"_0":"f11"}}},"toDetailCollection":{},"id":"1A14E261-BE34-420F-8068-2330AF99CCBF"},{"id":"7374FFE1-A426-418B-91E2-F287FDF18A99","toDetailCollection":{},"fromDetail":{"output":{"function_keys":{"_0":"f5"}},"display":"F5"}},{"fromDetail":{"display":"F9","output":{"function_keys":{"_0":"f9"}}},"toDetailCollection":{},"id":"76385AD1-B251-4C12-88CF-E3AB97224DD6"},{"fromDetail":{"output":{"controls_and_symbols":{"_0":"escape"}},"display":"escape","isSFSymbol":true},"unitSize":1.5,"id":"7721D658-05FF-4B06-B094-3D9ECEF6E904","toDetailCollection":{}},{"fromDetail":{"output":{"function_keys":{"_0":"f8"}},"display":"F8"},"id":"B6DF41AF-D104-4CFD-BF93-230320650E28","toDetailCollection":{}},{"id":"CE94CF19-4EA4-47BA-A12A-98131F108484","fromDetail":{"output":{"function_keys":{"_0":"f2"}},"display":"F2"},"toDetailCollection":{}},{"fromDetail":{"output":{"function_keys":{"_0":"f6"}},"display":"F6"},"id":"C62CCB0E-E24E-4139-9F53-936F4D83657D","toDetailCollection":{}},{"id":"17981D3D-798C-4829-8588-FAA510C2831F","toDetailCollection":{},"fromDetail":{"display":"F12","output":{"function_keys":{"_0":"f12"}}}}],"arrow_right":{"keyShape":"arrow_LR","id":"CE622A48-69B1-4B16-A5EC-42A42AE3C125","toDetailCollection":{},"fromDetail":{"output":{"arrow_keys":{"_0":"right_arrow"}},"display":"arrowtriangle.right.fill","isSFSymbol":true}},"row5":[{"id":"81557D30-7293-44CE-9B43-6FEB541933D5","fromDetail":{"output":{"international_keys":{"_0":"international1"}},"display":"_"},"toDetailCollection":{"condition0":{"layer0":{"isCustomized_tap":true,"withModifier_tap":{},"outputAndDisplay_tap":{"display":"J","layerKey":"layer0","output":{"letter_keys":{"_0":"j"}}}}}}},{"fromDetail":{"display":"X","output":{"letter_keys":{"_0":"x"}}},"id":"2D609F40-F473-485A-AA40-75E98B231654","toDetailCollection":{"condition0":{"layer0":{"outputAndDisplay_tap":{"output":{"controls_and_symbols":{"_0":"slash"}},"layerKey":"layer0","display":"\/"},"withModifier_tap":{},"isCustomized_tap":true}}}},{"fromDetail":{"display":"N","output":{"letter_keys":{"_0":"n"}}},"toDetailCollection":{"condition0":{"layer0":{"outputAndDisplay_tap":{"layerKey":"layer0","output":{"shift_symbols":{"_0":"colon"}},"display":":"},"withModifier_tap":{},"isCustomized_tap":true}}},"id":"B4397938-A015-4778-B3EA-86A27E21EE8B"},{"fromDetail":{"output":{"letter_keys":{"_0":"c"}},"display":"C"},"toDetailCollection":{"condition0":{"layer0":{"isCustomized_tap":true,"outputAndDisplay_tap":{"output":{"controls_and_symbols":{"_0":"comma"}},"display":",","layerKey":"layer0"},"withModifier_tap":{}}}},"id":"9A3FD642-9692-4148-826F-B415D646C540"},{"toDetailCollection":{},"unitSize":1.75,"fromDetail":{"output":{"modifier_keys":{"_0":"right_shift"}},"display":"shift","isSFSymbol":true},"id":"6755F193-22AE-49B2-A014-7CF7ED430C64"},{"toDetailCollection":{"condition0":{"layer0":{"isCustomized_tap":true,"withModifier_tap":{},"outputAndDisplay_tap":{"display":";","output":{"controls_and_symbols":{"_0":"semicolon"}},"layerKey":"layer0"}}}},"id":"591FEA93-63F1-43E5-813C-0A28AA9E0300","fromDetail":{"display":"B","output":{"letter_keys":{"_0":"b"}}}},{"fromDetail":{"display":"M","output":{"letter_keys":{"_0":"m"}}},"toDetailCollection":{"condition0":{"layer0":{"isCustomized_tap":true,"outputAndDisplay_tap":{"display":"W","layerKey":"layer0","output":{"letter_keys":{"_0":"w"}}},"withModifier_tap":{}}}},"id":"D2CE0275-38A7-46D4-AD9B-23AB10DB103D"},{"fromDetail":{"output":{"letter_keys":{"_0":"v"}},"display":"V"},"toDetailCollection":{"condition0":{"layer0":{"isCustomized_tap":true,"withModifier_tap":{},"outputAndDisplay_tap":{"output":{"controls_and_symbols":{"_0":"period"}},"layerKey":"layer0","display":"."}}}},"id":"C2342581-A15B-4F0E-B207-94C9FBDBED63"},{"id":"3F77E035-C851-4A19-8A33-46FCD6B53F6E","toDetailCollection":{},"fromDetail":{"display":"Z","output":{"letter_keys":{"_0":"z"}}}},{"toDetailCollection":{"condition0":{"layer0":{"isCustomized_tap":true,"outputAndDisplay_tap":{"output":{"letter_keys":{"_0":"l"}},"layerKey":"layer0","display":"L"},"withModifier_tap":{}}}},"id":"C60E34ED-A4BD-4A0A-98D8-A75F8CDCF9E9","fromDetail":{"display":".","output":{"controls_and_symbols":{"_0":"period"}}}},{"id":"E906A400-90B3-4F36-AF0C-09D2F1CF399C","toDetailCollection":{"condition0":{"layer0":{"outputAndDisplay_tap":{"layerKey":"layer0","output":{"letter_keys":{"_0":"b"}},"display":"B"},"isCustomized_tap":true,"withModifier_tap":{}}}},"fromDetail":{"display":"\/","output":{"controls_and_symbols":{"_0":"slash"}}}},{"toDetailCollection":{"condition0":{"layer0":{"withModifier_tap":{},"isCustomized_tap":true,"outputAndDisplay_tap":{"output":{"letter_keys":{"_0":"m"}},"display":"M","layerKey":"layer0"}}}},"id":"1B08A8D6-AD91-4188-B1F0-3E6A1E969874","fromDetail":{"output":{"controls_and_symbols":{"_0":"comma"}},"display":","}},{"fromDetail":{"output":{"modifier_keys":{"_0":"left_shift"}},"isSFSymbol":true,"display":"shift"},"toDetailCollection":{},"unitSize":1.75,"id":"40D48502-7BB9-4A74-A056-E69D079F6496"}],"idsInOrderRow3":[{"id":"72B38B73-0321-450F-9F2F-1A781A19A2CF"},{"id":"43D86F0A-5AA8-4820-80B3-9A7226863D02"},{"id":"586EF1EB-7F3D-4898-A04B-5D2617ACCC75"},{"id":"B8297DFB-D39F-442D-8A2C-24EB416515BB"},{"id":"76E2FDA5-355A-452E-9AC2-0ABBCFFA9E45"},{"id":"6E588C0B-5AAD-4255-9989-5D565FE9D3F7"},{"id":"D6F45AC0-6E55-409C-A2F5-2FF3392755CC"},{"id":"6677D693-3F3E-41F3-8E00-D5E284E5322E"},{"id":"DEB151A6-3FB9-437A-89F1-54C8E3029309"},{"id":"A14825CA-BF08-41C4-A4EF-E3B4717C4A4B"},{"id":"30E76702-5F6D-42B5-9070-D01E2D4C6896"},{"id":"47CDFBED-54D1-4086-B3E4-A741AF5F3090"},{"id":"32E09B93-2246-4DE7-9CA7-A743C20EA548"},{"id":"C61D9C59-F8C2-4CCC-B9FA-8791DD959A2F"}],"row3":[{"fromDetail":{"output":{"controls_and_symbols":{"_0":"tab"}},"isSFSymbol":true,"display":"arrow.right.to.line"},"toDetailCollection":{},"id":"72B38B73-0321-450F-9F2F-1A781A19A2CF"},{"id":"586EF1EB-7F3D-4898-A04B-5D2617ACCC75","fromDetail":{"output":{"letter_keys":{"_0":"w"}},"display":"W"},"toDetailCollection":{"condition0":{"layer0":{"isCustomized_tap":true,"outputAndDisplay_tap":{"display":"Y","layerKey":"layer0","output":{"letter_keys":{"_0":"y"}}},"withModifier_tap":{}}}}},{"unitSize":1.5,"fromDetail":{"isSFSymbol":true,"display":"return","output":{"controls_and_symbols":{"_0":"return_or_enter"}}},"id":"C61D9C59-F8C2-4CCC-B9FA-8791DD959A2F","toDetailCollection":{},"keyShape":"enter_JIS"},{"fromDetail":{"display":"[","output":{"controls_and_symbols":{"_0":"open_square_bracket_jis"}}},"toDetailCollection":{"condition0":{"layer0":{"isCustomized_tap":true,"withModifier_tap":{},"outputAndDisplay_tap":{"output":{"letter_keys":{"_0":"q"}},"display":"Q","layerKey":"layer0"}}}},"id":"32E09B93-2246-4DE7-9CA7-A743C20EA548"},{"toDetailCollection":{"condition0":{"layer0":{"outputAndDisplay_tap":{"output":{"letter_keys":{"_0":"k"}},"layerKey":"layer0","display":"K"},"isCustomized_tap":true,"withModifier_tap":{}}}},"id":"6677D693-3F3E-41F3-8E00-D5E284E5322E","fromDetail":{"output":{"letter_keys":{"_0":"u"}},"display":"U"}},{"id":"6E588C0B-5AAD-4255-9989-5D565FE9D3F7","toDetailCollection":{"condition0":{"layer0":{"withModifier_tap":{},"outputAndDisplay_tap":{"layerKey":"layer0","display":"-","output":{"controls_and_symbols":{"_0":"hyphen"}}},"isCustomized_tap":true}}},"fromDetail":{"display":"T","output":{"letter_keys":{"_0":"t"}}}},{"id":"76E2FDA5-355A-452E-9AC2-0ABBCFFA9E45","fromDetail":{"output":{"letter_keys":{"_0":"r"}},"display":"R"},"toDetailCollection":{"condition0":{"layer0":{"outputAndDisplay_tap":{"display":"O","output":{"letter_keys":{"_0":"o"}},"layerKey":"layer0"},"withModifier_tap":{},"isCustomized_tap":true}}}},{"id":"47CDFBED-54D1-4086-B3E4-A741AF5F3090","fromDetail":{"display":"@","output":{"controls_and_symbols":{"_0":"commercial_at_jis"}}},"toDetailCollection":{"condition0":{"layer0":{"isCustomized_tap":true,"outputAndDisplay_tap":{"output":{"letter_keys":{"_0":"x"}},"display":"X","layerKey":"layer0"},"withModifier_tap":{}}}}},{"fromDetail":{"output":{"letter_keys":{"_0":"q"}},"display":"Q"},"toDetailCollection":{"condition0":{"layer0":{"isCustomized_tap":true,"withModifier_tap":{},"outputAndDisplay_tap":{"output":{"letter_keys":{"_0":"p"}},"layerKey":"layer0","display":"P"}}}},"id":"43D86F0A-5AA8-4820-80B3-9A7226863D02"},{"fromDetail":{"display":"O","output":{"letter_keys":{"_0":"o"}}},"toDetailCollection":{"condition0":{"layer0":{"withModifier_tap":{},"outputAndDisplay_tap":{"layerKey":"layer0","display":"H","output":{"letter_keys":{"_0":"h"}}},"isCustomized_tap":true}}},"id":"A14825CA-BF08-41C4-A4EF-E3B4717C4A4B"},{"toDetailCollection":{"condition0":{"layer0":{"withModifier_tap":{},"isCustomized_tap":true,"outputAndDisplay_tap":{"display":"^","layerKey":"layer0","output":{"shift_symbols":{"_0":"caret"}}}}}},"id":"D6F45AC0-6E55-409C-A2F5-2FF3392755CC","fromDetail":{"output":{"letter_keys":{"_0":"y"}},"display":"Y"}},{"id":"30E76702-5F6D-42B5-9070-D01E2D4C6896","fromDetail":{"display":"P","output":{"letter_keys":{"_0":"p"}}},"toDetailCollection":{"condition0":{"layer0":{"withModifier_tap":{},"isCustomized_tap":true,"outputAndDisplay_tap":{"output":{"letter_keys":{"_0":"f"}},"layerKey":"layer0","display":"F"}}}}},{"id":"DEB151A6-3FB9-437A-89F1-54C8E3029309","fromDetail":{"output":{"letter_keys":{"_0":"i"}},"display":"I"},"toDetailCollection":{"condition0":{"layer0":{"isCustomized_tap":true,"withModifier_tap":{},"outputAndDisplay_tap":{"layerKey":"layer0","output":{"letter_keys":{"_0":"d"}},"display":"D"}}}}},{"fromDetail":{"output":{"letter_keys":{"_0":"e"}},"display":"E"},"toDetailCollection":{"condition0":{"layer0":{"isCustomized_tap":true,"withModifier_tap":{},"outputAndDisplay_tap":{"display":"U","output":{"letter_keys":{"_0":"u"}},"layerKey":"layer0"}}}},"id":"B8297DFB-D39F-442D-8A2C-24EB416515BB"}],"row6":[{"toDetailCollection":{},"id":"666632C3-2334-491B-AEA2-34BF469114A5","fromDetail":{"isSFSymbol":true,"output":{"modifier_keys":{"_0":"caps_lock"}},"display":"capslock"}},{"unitSize":1.25,"id":"5D37E315-2B6C-4909-ABF9-0CBA51084534","fromDetail":{"display":"command","output":{"modifier_keys":{"_0":"left_command"}},"isSFSymbol":true},"toDetailCollection":{}},{"fromDetail":{"display":"かな","output":{"japanese":{"_0":"kana"}}},"unitSize":1.25,"toDetailCollection":{},"id":"7B070B62-B30D-47F1-90E6-413C6EE74B46"},{"toDetailCollection":{},"id":"D784821C-3810-4E51-A2C5-5DF143EECE85","fromDetail":{"output":{"modifier_keys":{"_0":"left_option"}},"display":"option","isSFSymbol":true}},{"unitSize":1.25,"fromDetail":{"isSFSymbol":true,"display":"command","output":{"modifier_keys":{"_0":"right_command"}}},"toDetailCollection":{},"id":"692DF993-EE19-4318-A8F3-901003C189D3"},{"toDetailCollection":{},"fromDetail":{"display":"英数","output":{"japanese":{"_0":"eisuu"}}},"id":"32824DF8-E97D-41A8-A8FD-8D2165313CBC","unitSize":1.25},{"toDetailCollection":{},"id":"520808FC-E0D8-4843-B008-641F8328F0AC","fromDetail":{"isSFSymbol":true,"output":{"modifier_keys":{"_0":"keyboard_fn"}},"display":"globe"}},{"toDetailCollection":{},"unitSize":3.5,"fromDetail":{"display":"␣","output":{"controls_and_symbols":{"_0":"spacebar"}}},"id":"339D97CE-7545-41E1-9078-C04F60EA95A0"}],"row4":[{"fromDetail":{"output":{"controls_and_symbols":{"_0":"close_square_bracket_jis"}},"display":"]"},"toDetailCollection":{"condition0":{"layer0":{"withModifier_tap":{},"isCustomized_tap":true,"outputAndDisplay_tap":{"layerKey":"layer0","output":{"letter_keys":{"_0":"v"}},"display":"V"}}}},"id":"6CC29A37-EB0A-4AE6-BB3A-CF98EC6FDC15"},{"fromDetail":{"output":{"letter_keys":{"_0":"f"}},"display":"F"},"id":"CC2EF530-0AAD-46D1-8B0C-6F8F35700942","toDetailCollection":{"condition0":{"layer0":{"outputAndDisplay_tap":{"display":"A","layerKey":"layer0","output":{"letter_keys":{"_0":"a"}}},"withModifier_tap":{},"isCustomized_tap":true}}}},{"fromDetail":{"display":"J","output":{"letter_keys":{"_0":"j"}}},"toDetailCollection":{"condition0":{"layer0":{"withModifier_tap":{},"isCustomized_tap":true,"outputAndDisplay_tap":{"output":{"letter_keys":{"_0":"g"}},"layerKey":"layer0","display":"G"}}}},"id":"DC19D8B1-9411-4D00-8257-57A0E88B229A"},{"id":"E9E6F415-8585-4BAB-9802-84BCE23E9107","fromDetail":{"output":{"letter_keys":{"_0":"s"}},"display":"S"},"toDetailCollection":{"condition0":{"layer0":{"isCustomized_tap":true,"outputAndDisplay_tap":{"display":"I","layerKey":"layer0","output":{"letter_keys":{"_0":"i"}}},"withModifier_tap":{}}}}},{"toDetailCollection":{"condition0":{"layer0":{"outputAndDisplay_tap":{"layerKey":"layer0","output":{"international_keys":{"_0":"international1"}},"display":"_"},"isCustomized_tap":true,"withModifier_tap":{}}}},"fromDetail":{"display":"H","output":{"letter_keys":{"_0":"h"}}},"id":"0F67544B-79C1-4E01-8D33-B358327B5F05"},{"id":"0A2EF3A1-02A2-47D1-89E3-5FD639462BE4","fromDetail":{"output":{"controls_and_symbols":{"_0":"single_quotation_or_colon"}},"display":":"},"toDetailCollection":{"condition0":{"layer0":{"outputAndDisplay_tap":{"output":{"letter_keys":{"_0":"r"}},"display":"R","layerKey":"layer0"},"withModifier_tap":{},"isCustomized_tap":true}}}},{"fromDetail":{"display":"A","output":{"letter_keys":{"_0":"a"}}},"id":"A65A7500-8067-4C58-9D8C-56C0E26B0602","toDetailCollection":{"condition0":{"layer0":{"isCustomized_tap":true,"outputAndDisplay_tap":{"layerKey":"layer0","display":"C","output":{"letter_keys":{"_0":"c"}}},"withModifier_tap":{}}}}},{"fromDetail":{"display":"D","output":{"letter_keys":{"_0":"d"}}},"toDetailCollection":{"condition0":{"layer0":{"outputAndDisplay_tap":{"output":{"letter_keys":{"_0":"e"}},"display":"E","layerKey":"layer0"},"isCustomized_tap":true,"withModifier_tap":{}}}},"id":"5933351E-9E52-4FFC-960B-4682F54E0E33"},{"id":"5B37AF98-20A7-441B-B6DC-3D251AA6DA5E","toDetailCollection":{},"fromDetail":{"display":"control","output":{"modifier_keys":{"_0":"left_control"}},"isSFSymbol":true},"unitSize":1.25},{"toDetailCollection":{"condition0":{"layer0":{"withModifier_tap":{},"isCustomized_tap":true,"outputAndDisplay_tap":{"output":{"letter_keys":{"_0":"n"}},"layerKey":"layer0","display":"N"}}}},"fromDetail":{"display":"L","output":{"letter_keys":{"_0":"l"}}},"id":"708E3E6E-FA51-49FB-8E4F-DEC3F8E08FE6"},{"id":"B293A086-5B36-4647-A7B3-C4BB833B73D1","fromDetail":{"display":"G","output":{"letter_keys":{"_0":"g"}}},"toDetailCollection":{"condition0":{"layer0":{"isCustomized_tap":true,"withModifier_tap":{},"outputAndDisplay_tap":{"layerKey":"layer0","display":"@","output":{"shift_symbols":{"_0":"commercial_at"}}}}}}},{"fromDetail":{"display":"K","output":{"letter_keys":{"_0":"k"}}},"id":"B371E055-8A22-4B90-96A8-7DA77C52AC1D","toDetailCollection":{"condition0":{"layer0":{"withModifier_tap":{},"isCustomized_tap":true,"outputAndDisplay_tap":{"layerKey":"layer0","output":{"letter_keys":{"_0":"t"}},"display":"T"}}}}},{"fromDetail":{"display":";","output":{"controls_and_symbols":{"_0":"semicolon"}}},"toDetailCollection":{"condition0":{"layer0":{"isCustomized_tap":true,"outputAndDisplay_tap":{"display":"S","output":{"letter_keys":{"_0":"s"}},"layerKey":"layer0"},"withModifier_tap":{}}}},"id":"E214B737-667B-4B8A-A49F-A1485BF81C33"}],"arrow_left":{"id":"0EAB1D8D-43F1-4D1D-B731-541B4D4B9797","keyShape":"arrow_LR","toDetailCollection":{},"fromDetail":{"display":"arrowtriangle.left.fill","isSFSymbol":true,"output":{"arrow_keys":{"_0":"left_arrow"}}}},"idsInOrderRow1":[{"id":"7721D658-05FF-4B06-B094-3D9ECEF6E904"},{"id":"4F3C2609-8EB1-4663-8690-A8639A375AEA"},{"id":"CE94CF19-4EA4-47BA-A12A-98131F108484"},{"id":"D219841C-9444-4BD6-88E3-481251E9F5B0"},{"id":"3A8E6CAE-163D-4999-9200-CF8534831A27"},{"id":"7374FFE1-A426-418B-91E2-F287FDF18A99"},{"id":"C62CCB0E-E24E-4139-9F53-936F4D83657D"},{"id":"1253EBB3-3856-4834-A662-D832BEE5F19C"},{"id":"B6DF41AF-D104-4CFD-BF93-230320650E28"},{"id":"76385AD1-B251-4C12-88CF-E3AB97224DD6"},{"id":"A27B70DD-499D-4A45-A249-30A98821F6BB"},{"id":"1A14E261-BE34-420F-8068-2330AF99CCBF"},{"id":"17981D3D-798C-4829-8588-FAA510C2831F"}],"idsInOrderRow6":[{"id":"666632C3-2334-491B-AEA2-34BF469114A5"},{"id":"D784821C-3810-4E51-A2C5-5DF143EECE85"},{"id":"5D37E315-2B6C-4909-ABF9-0CBA51084534"},{"id":"32824DF8-E97D-41A8-A8FD-8D2165313CBC"},{"id":"339D97CE-7545-41E1-9078-C04F60EA95A0"},{"id":"7B070B62-B30D-47F1-90E6-413C6EE74B46"},{"id":"692DF993-EE19-4318-A8F3-901003C189D3"},{"id":"520808FC-E0D8-4843-B008-641F8328F0AC"}],"idsInOrderRow5":[{"id":"40D48502-7BB9-4A74-A056-E69D079F6496"},{"id":"3F77E035-C851-4A19-8A33-46FCD6B53F6E"},{"id":"2D609F40-F473-485A-AA40-75E98B231654"},{"id":"9A3FD642-9692-4148-826F-B415D646C540"},{"id":"C2342581-A15B-4F0E-B207-94C9FBDBED63"},{"id":"591FEA93-63F1-43E5-813C-0A28AA9E0300"},{"id":"B4397938-A015-4778-B3EA-86A27E21EE8B"},{"id":"D2CE0275-38A7-46D4-AD9B-23AB10DB103D"},{"id":"1B08A8D6-AD91-4188-B1F0-3E6A1E969874"},{"id":"C60E34ED-A4BD-4A0A-98D8-A75F8CDCF9E9"},{"id":"E906A400-90B3-4F36-AF0C-09D2F1CF399C"},{"id":"81557D30-7293-44CE-9B43-6FEB541933D5"},{"id":"6755F193-22AE-49B2-A014-7CF7ED430C64"}],"row2":[{"id":"F3C60F93-5B4A-40D7-8B7B-DB3F11483F05","fromDetail":{"display":"6","output":{"number_keys":{"_0":"six"}}},"toDetailCollection":{}},{"unitSize":1.25,"id":"0904F2E5-A5FC-4E23-8FC6-424A2CDC9A77","fromDetail":{"isSFSymbol":true,"display":"delete.left","output":{"controls_and_symbols":{"_0":"delete_or_backspace"}}},"toDetailCollection":{}},{"toDetailCollection":{},"fromDetail":{"output":{"number_keys":{"_0":"five"}},"display":"5"},"id":"2F5AD8FB-E504-436D-A25A-A0C096D61E8C"},{"fromDetail":{"output":{"number_keys":{"_0":"seven"}},"display":"7"},"toDetailCollection":{},"id":"E2D931E5-C342-4B1D-9235-F445F520549B"},{"toDetailCollection":{},"id":"154B1993-1F7D-482A-81E1-E44533AA3DE3","fromDetail":{"display":"0","output":{"number_keys":{"_0":"zero"}}}},{"id":"7766049F-E168-4BC0-81C2-F4DB2D6C4285","fromDetail":{"display":"2","output":{"number_keys":{"_0":"two"}}},"toDetailCollection":{}},{"toDetailCollection":{},"fromDetail":{"output":{"number_keys":{"_0":"four"}},"display":"4"},"id":"7EA61C71-0E79-4D9A-9D69-627EA48BE925"},{"toDetailCollection":{},"fromDetail":{"display":"9","output":{"number_keys":{"_0":"nine"}}},"id":"56F043B3-4FFA-44A6-8828-08333978C4A0"},{"id":"DF5E347B-D751-403B-A425-8E44F507EE13","fromDetail":{"output":{"controls_and_symbols":{"_0":"hyphen"}},"display":"-"},"toDetailCollection":{"condition0":{"layer0":{"isCustomized_tap":true,"outputAndDisplay_tap":{"display":"[","layerKey":"layer0","output":{"controls_and_symbols":{"_0":"open_square_bracket"}}},"withModifier_tap":{}}}}},{"toDetailCollection":{},"fromDetail":{"display":"8","output":{"number_keys":{"_0":"eight"}}},"id":"9AFA3821-693A-4103-837F-6DE254CDC213"},{"toDetailCollection":{},"id":"C3A6D036-7C38-4344-AC8A-20FCAEBAB12B","fromDetail":{"output":{"number_keys":{"_0":"three"}},"display":"3"}},{"toDetailCollection":{"condition0":{"layer0":{"withModifier_tap":{},"outputAndDisplay_tap":{"display":"]","layerKey":"layer0","output":{"controls_and_symbols":{"_0":"close_square_bracket"}}},"isCustomized_tap":true}}},"fromDetail":{"display":"^","output":{"controls_and_symbols":{"_0":"equal_sign_or_caret"}}},"id":"4CD43EBC-5F50-4696-915D-F45923BBDE85"},{"unitSize":1.25,"toDetailCollection":{},"id":"F08DCBE3-E6D1-4601-883C-5783EB1B8838","fromDetail":{"display":"1","output":{"number_keys":{"_0":"one"}}}},{"toDetailCollection":{},"fromDetail":{"output":{"international_keys":{"_0":"international3"}},"display":"\\"},"id":"EC5CB708-8070-47E1-A25F-80E317FCD12E"}],"rowIndex_arrow":{"row6":{}},"idsInOrderRow2":[{"id":"F08DCBE3-E6D1-4601-883C-5783EB1B8838"},{"id":"7766049F-E168-4BC0-81C2-F4DB2D6C4285"},{"id":"C3A6D036-7C38-4344-AC8A-20FCAEBAB12B"},{"id":"7EA61C71-0E79-4D9A-9D69-627EA48BE925"},{"id":"2F5AD8FB-E504-436D-A25A-A0C096D61E8C"},{"id":"F3C60F93-5B4A-40D7-8B7B-DB3F11483F05"},{"id":"E2D931E5-C342-4B1D-9235-F445F520549B"},{"id":"9AFA3821-693A-4103-837F-6DE254CDC213"},{"id":"56F043B3-4FFA-44A6-8828-08333978C4A0"},{"id":"154B1993-1F7D-482A-81E1-E44533AA3DE3"},{"id":"DF5E347B-D751-403B-A425-8E44F507EE13"},{"id":"4CD43EBC-5F50-4696-915D-F45923BBDE85"},{"id":"EC5CB708-8070-47E1-A25F-80E317FCD12E"},{"id":"0904F2E5-A5FC-4E23-8FC6-424A2CDC9A77"}],"arrow_down":{"toDetailCollection":{},"fromDetail":{"display":"arrowtriangle.down.fill","output":{"arrow_keys":{"_0":"down_arrow"}},"isSFSymbol":true},"id":"1172DAE0-6CC7-4129-A07D-425951623D57","keyShape":"arrow_Down"}},"tenkeyRows":{"idsInOrderRow3":[{"id":"9C2538F4-D16B-4286-A6A9-43C6D9F69D98"},{"id":"CBD31261-EBB7-407D-83EE-B5276312EFED"},{"id":"4F09A345-BE93-41A8-BFA1-D0FEED3ED1C7"},{"id":"DC57907E-B4C2-463B-9124-1FE30427657E"}],"row1":[{"fromDetail":{"display":"F19","output":{"function_keys":{"_0":"f19"}}},"toDetailCollection":{},"id":"C84F4958-11D2-43F3-A1C5-A71198BB29E1"},{"fromDetail":{"display":"F18","output":{"function_keys":{"_0":"f18"}}},"toDetailCollection":{},"id":"FFFEB063-AAE8-48E2-8018-827EF73EE3BF"},{"fromDetail":{"output":{"function_keys":{"_0":"f16"}},"display":"F16"},"toDetailCollection":{},"id":"AA047090-6BED-4CE6-BE7F-86C2D90189A4"},{"toDetailCollection":{},"id":"8781FCBA-CAB8-4CFD-9CD7-A02B2FE885C9","fromDetail":{"display":"F17","output":{"function_keys":{"_0":"f17"}}}}],"idsInOrderRow1":[{"id":"AA047090-6BED-4CE6-BE7F-86C2D90189A4"},{"id":"8781FCBA-CAB8-4CFD-9CD7-A02B2FE885C9"},{"id":"FFFEB063-AAE8-48E2-8018-827EF73EE3BF"},{"id":"C84F4958-11D2-43F3-A1C5-A71198BB29E1"}],"row4":[{"fromDetail":{"output":{"keypad_keys":{"_0":"keypad_5"}},"display":"5"},"toDetailCollection":{},"id":"1FDFF9B8-A8FE-4DC6-A4C9-679B5EBD78B3"},{"fromDetail":{"output":{"keypad_keys":{"_0":"keypad_4"}},"display":"4"},"id":"6D1C50B8-7673-4837-A589-9E545AFC12D9","toDetailCollection":{}},{"id":"73413325-3668-4565-9C7C-7FE3E180AC18","toDetailCollection":{},"fromDetail":{"display":"6","output":{"keypad_keys":{"_0":"keypad_6"}}}},{"fromDetail":{"output":{"keypad_keys":{"_0":"keypad_plus"}},"display":"+"},"toDetailCollection":{},"id":"DF0B8100-DD0D-4E66-9696-93E0E2DA3ECD"}],"idsInOrderRow2":[{"id":"13F049ED-DFED-4F51-AF7A-DE242AAD4F6A"},{"id":"45227D13-CBD1-4F76-AFBC-554B4C4D80BF"},{"id":"D27DBD66-3B96-4031-BCC5-A5CCD4A0AC5A"},{"id":"10264C35-C7D5-415D-8B15-87062DD07FD3"}],"row3":[{"id":"4F09A345-BE93-41A8-BFA1-D0FEED3ED1C7","toDetailCollection":{},"fromDetail":{"display":"9","output":{"keypad_keys":{"_0":"keypad_9"}}}},{"toDetailCollection":{},"id":"9C2538F4-D16B-4286-A6A9-43C6D9F69D98","fromDetail":{"display":"7","output":{"keypad_keys":{"_0":"keypad_7"}}}},{"fromDetail":{"output":{"keypad_keys":{"_0":"keypad_hyphen"}},"display":"-"},"toDetailCollection":{},"id":"DC57907E-B4C2-463B-9124-1FE30427657E"},{"id":"CBD31261-EBB7-407D-83EE-B5276312EFED","fromDetail":{"output":{"keypad_keys":{"_0":"keypad_8"}},"display":"8"},"toDetailCollection":{}}],"idsInOrderRow6":[{"id":"D5EC3891-3B3B-4A2A-91E2-2DBDE399E50D"},{"id":"BC10A733-9624-4D69-9A3F-A965880BA5FF"},{"id":"A4232F8E-A756-47D6-B5B9-3F58A9238067"}],"enableArrowKeys":false,"row5":[{"keyShape":"enter_Tenkey","toDetailCollection":{},"fromDetail":{"display":"projective","isSFSymbol":true,"output":{"keypad_keys":{"_0":"keypad_enter"}}},"id":"C40C8752-C47F-4816-A4A2-E15A2CF26ED4"},{"toDetailCollection":{},"id":"7CEE018D-7E98-4C40-96B9-7D1E26A0D862","fromDetail":{"display":"3","output":{"keypad_keys":{"_0":"keypad_3"}}}},{"fromDetail":{"output":{"keypad_keys":{"_0":"keypad_2"}},"display":"2"},"toDetailCollection":{},"id":"BBC04D2A-E903-4A10-8BCE-13037CB67FAB"},{"toDetailCollection":{},"id":"B2319D73-AFA8-48E7-A7F4-B6D0C01AE899","fromDetail":{"display":"1","output":{"keypad_keys":{"_0":"keypad_1"}}}}],"arrow_up":{"keyShape":"arrow_Up","id":"C9BE9F11-FC61-4684-A5D5-1C75EC0C286B","fromDetail":{"output":{"arrow_keys":{"_0":"up_arrow"}},"display":"arrowtriangle.up.fill","isSFSymbol":true},"toDetailCollection":{}},"rowIndex_arrow":{"row6":{}},"idsInOrderRow4":[{"id":"6D1C50B8-7673-4837-A589-9E545AFC12D9"},{"id":"1FDFF9B8-A8FE-4DC6-A4C9-679B5EBD78B3"},{"id":"73413325-3668-4565-9C7C-7FE3E180AC18"},{"id":"DF0B8100-DD0D-4E66-9696-93E0E2DA3ECD"}],"arrow_left":{"toDetailCollection":{},"id":"E3CB865D-361E-4378-AC52-37981EEC4FAC","fromDetail":{"display":"arrowtriangle.left.fill","isSFSymbol":true,"output":{"arrow_keys":{"_0":"left_arrow"}}},"keyShape":"arrow_LR"},"arrow_down":{"keyShape":"arrow_Down","toDetailCollection":{},"id":"236641B3-672D-47E7-B575-CBE6CC91DA21","fromDetail":{"output":{"arrow_keys":{"_0":"down_arrow"}},"display":"arrowtriangle.down.fill","isSFSymbol":true}},"row6":[{"toDetailCollection":{},"fromDetail":{"display":".","output":{"keypad_keys":{"_0":"keypad_period"}}},"id":"A4232F8E-A756-47D6-B5B9-3F58A9238067"},{"fromDetail":{"display":"0","output":{"keypad_keys":{"_0":"keypad_0"}}},"id":"D5EC3891-3B3B-4A2A-91E2-2DBDE399E50D","toDetailCollection":{}},{"id":"BC10A733-9624-4D69-9A3F-A965880BA5FF","fromDetail":{"display":",","output":{"keypad_keys":{"_0":"keypad_comma"}}},"toDetailCollection":{}}],"row2":[{"fromDetail":{"output":{"keypad_keys":{"_0":"keypad_slash"}},"display":"\/"},"id":"D27DBD66-3B96-4031-BCC5-A5CCD4A0AC5A","toDetailCollection":{}},{"toDetailCollection":{},"id":"13F049ED-DFED-4F51-AF7A-DE242AAD4F6A","fromDetail":{"display":"clear","output":{"others":{"_0":"clear"}}}},{"fromDetail":{"display":"*","output":{"keypad_keys":{"_0":"keypad_asterisk"}}},"toDetailCollection":{},"id":"10264C35-C7D5-415D-8B15-87062DD07FD3"},{"id":"45227D13-CBD1-4F76-AFBC-554B4C4D80BF","toDetailCollection":{},"fromDetail":{"output":{"keypad_keys":{"_0":"keypad_equal_sign"}},"display":"="}}],"arrow_right":{"id":"58527F74-E02D-4174-9EAA-9CF258B18FA5","toDetailCollection":{},"keyShape":"arrow_LR","fromDetail":{"output":{"arrow_keys":{"_0":"right_arrow"}},"display":"arrowtriangle.right.fill","isSFSymbol":true}},"idsInOrderRow5":[{"id":"B2319D73-AFA8-48E7-A7F4-B6D0C01AE899"},{"id":"BBC04D2A-E903-4A10-8BCE-13037CB67FAB"},{"id":"7CEE018D-7E98-4C40-96B9-7D1E26A0D862"},{"id":"C40C8752-C47F-4816-A4A2-E15A2CF26ED4"}]},"isEnableTenkey":false,"isEnableSub":false},"mouse":{"subRows":{"idsInOrderRow2":[{"id":"AB23C957-04F2-4B98-B2C3-B306723F0740"}],"idsInOrderRow3":[{"id":"7CA98446-E87F-40AA-9553-3ECA091C415A"}],"row2":[{"id":"AB23C957-04F2-4B98-B2C3-B306723F0740","fromDetail":{"display":"A","output":{"letter_keys":{"_0":"a"}}},"toDetailCollection":{}}],"row4":[{"id":"D500C0B8-50A2-4946-844A-7C394825DAC7","fromDetail":{"output":{"letter_keys":{"_0":"a"}},"display":"A"},"toDetailCollection":{}}],"idsInOrderRow1":[{"id":"C9183EEB-FE8D-4370-8849-0FDF16418448"}],"idsInOrderRow5":[{"id":"895D7FDC-B54E-4B11-972B-1D3712DD7A26"}],"arrow_left":{"keyShape":"arrow_LR","fromDetail":{"display":"arrowtriangle.left.fill","output":{"arrow_keys":{"_0":"left_arrow"}},"isSFSymbol":true},"id":"E7941AFD-B923-457F-8C48-9801F29BC6EB","toDetailCollection":{}},"idsInOrderRow6":[{"id":"F277A3DF-1F0F-42FD-A287-8F3EC710CB7F"}],"arrow_right":{"toDetailCollection":{},"keyShape":"arrow_LR","fromDetail":{"output":{"arrow_keys":{"_0":"right_arrow"}},"isSFSymbol":true,"display":"arrowtriangle.right.fill"},"id":"1DBAF9BF-47F9-4B8D-A695-F15CDAC48DF5"},"row3":[{"fromDetail":{"output":{"letter_keys":{"_0":"a"}},"display":"A"},"toDetailCollection":{},"id":"7CA98446-E87F-40AA-9553-3ECA091C415A"}],"row5":[{"id":"895D7FDC-B54E-4B11-972B-1D3712DD7A26","fromDetail":{"display":"A","output":{"letter_keys":{"_0":"a"}}},"toDetailCollection":{}}],"enableArrowKeys":false,"row6":[{"fromDetail":{"output":{"letter_keys":{"_0":"a"}},"display":"A"},"id":"F277A3DF-1F0F-42FD-A287-8F3EC710CB7F","toDetailCollection":{}}],"row1":[{"toDetailCollection":{},"fromDetail":{"output":{"letter_keys":{"_0":"a"}},"display":"A"},"id":"C9183EEB-FE8D-4370-8849-0FDF16418448"}],"rowIndex_arrow":{"row6":{}},"arrow_up":{"fromDetail":{"output":{"arrow_keys":{"_0":"up_arrow"}},"display":"arrowtriangle.up.fill","isSFSymbol":true},"id":"39C498C8-AA56-47C5-B341-ADE7044ED470","toDetailCollection":{},"keyShape":"arrow_Up"},"arrow_down":{"id":"60D3B638-2AEA-4AF1-B0DA-5B9F30D2365C","fromDetail":{"isSFSymbol":true,"output":{"arrow_keys":{"_0":"down_arrow"}},"display":"arrowtriangle.down.fill"},"keyShape":"arrow_Down","toDetailCollection":{}},"idsInOrderRow4":[{"id":"D500C0B8-50A2-4946-844A-7C394825DAC7"}]},"tenkeyRows":{"arrow_up":{"id":"C4022A0F-2421-45F7-BE71-290FAE83E230","toDetailCollection":{},"keyShape":"arrow_Up","fromDetail":{"display":"arrowtriangle.up.fill","isSFSymbol":true,"output":{"arrow_keys":{"_0":"up_arrow"}}}},"rowIndex_arrow":{"row6":{}},"row4":[{"toDetailCollection":{},"id":"E7EDB079-39B5-4008-A98A-081FF22CB0E8","fromDetail":{"output":{"letter_keys":{"_0":"a"}},"display":"A"}}],"idsInOrderRow1":[{"id":"E308AE39-FA24-452B-A11E-117E55B165D4"}],"enableArrowKeys":false,"idsInOrderRow5":[{"id":"E2EC55CC-45F3-4801-A3D4-EA0D588C8BFE"}],"idsInOrderRow6":[{"id":"0F564C7A-7962-4C08-8114-D7F01C1B901A"}],"row3":[{"fromDetail":{"output":{"letter_keys":{"_0":"a"}},"display":"A"},"id":"E323E83E-D776-42FA-B8A1-988E5D7E0239","toDetailCollection":{}}],"arrow_left":{"toDetailCollection":{},"id":"3061E6AE-0B0C-4738-8D0C-B13B7A40BCBF","keyShape":"arrow_LR","fromDetail":{"output":{"arrow_keys":{"_0":"left_arrow"}},"isSFSymbol":true,"display":"arrowtriangle.left.fill"}},"idsInOrderRow2":[{"id":"E95BA1B8-F6FC-4D0A-A041-B65F7DFF8495"}],"idsInOrderRow4":[{"id":"E7EDB079-39B5-4008-A98A-081FF22CB0E8"}],"idsInOrderRow3":[{"id":"E323E83E-D776-42FA-B8A1-988E5D7E0239"}],"row2":[{"id":"E95BA1B8-F6FC-4D0A-A041-B65F7DFF8495","fromDetail":{"output":{"letter_keys":{"_0":"a"}},"display":"A"},"toDetailCollection":{}}],"arrow_down":{"toDetailCollection":{},"keyShape":"arrow_Down","fromDetail":{"display":"arrowtriangle.down.fill","isSFSymbol":true,"output":{"arrow_keys":{"_0":"down_arrow"}}},"id":"1FA19C3B-ECBE-4A4C-8F91-9547F1F30B41"},"row1":[{"id":"E308AE39-FA24-452B-A11E-117E55B165D4","fromDetail":{"output":{"letter_keys":{"_0":"a"}},"display":"A"},"toDetailCollection":{}}],"row5":[{"fromDetail":{"output":{"letter_keys":{"_0":"a"}},"display":"A"},"toDetailCollection":{},"id":"E2EC55CC-45F3-4801-A3D4-EA0D588C8BFE"}],"arrow_right":{"id":"A990A4C5-4072-419B-8FCC-A87038A5E83C","toDetailCollection":{},"keyShape":"arrow_LR","fromDetail":{"output":{"arrow_keys":{"_0":"right_arrow"}},"display":"arrowtriangle.right.fill","isSFSymbol":true}},"row6":[{"fromDetail":{"output":{"letter_keys":{"_0":"a"}},"display":"A"},"toDetailCollection":{},"id":"0F564C7A-7962-4C08-8114-D7F01C1B901A"}]},"isEnableTenkey":false,"mainRows":{"row6":[],"row2":[{"toDetailCollection":{},"fromDetail":{"output":{"mouse_buttons":{"_0":"button3"}},"display":"M click"},"id":"5A8DB14A-1F18-4389-A46D-9975EA41138D"},{"isSpacer":true,"toDetailCollection":{},"id":"F61E36F7-173C-4E72-BE98-2B2ED9005342","fromDetail":{"output":{"letter_keys":{"_0":"a"}},"display":"A"},"unitSize":0.5}],"idsInOrderRow1":[{"id":"99326D08-CB92-46DA-AEFA-52A647BDFD58"},{"id":"0D4FE843-AED2-4B46-9C20-770D4B0C721E"}],"enableArrowKeys":false,"idsInOrderRow2":[{"id":"F61E36F7-173C-4E72-BE98-2B2ED9005342"},{"id":"5A8DB14A-1F18-4389-A46D-9975EA41138D"}],"row1":[{"toDetailCollection":{},"id":"0D4FE843-AED2-4B46-9C20-770D4B0C721E","fromDetail":{"display":"R click","output":{"mouse_buttons":{"_0":"button2"}}}},{"fromDetail":{"output":{"mouse_buttons":{"_0":"button1"}},"display":"L click"},"toDetailCollection":{},"id":"99326D08-CB92-46DA-AEFA-52A647BDFD58"}],"idsInOrderRow6":[],"row3":[{"id":"9810826E-51FE-4B30-B957-5446CA40F15E","fromDetail":{"output":{"letter_keys":{"_0":"a"}},"display":"A"},"isSpacer":true,"toDetailCollection":{}}],"arrow_right":{"id":"E7921E58-6D3F-4C16-B264-3D51D6A94EB3","keyShape":"arrow_LR","toDetailCollection":{},"fromDetail":{"display":"arrowtriangle.right.fill","output":{"arrow_keys":{"_0":"right_arrow"}},"isSFSymbol":true}},"idsInOrderRow5":[],"row4":[{"toDetailCollection":{},"fromDetail":{"display":"A","output":{"letter_keys":{"_0":"a"}}},"id":"DD644FC4-F6E6-42E4-B774-26AA8FBDC786","isSpacer":true}],"arrow_up":{"fromDetail":{"isSFSymbol":true,"output":{"arrow_keys":{"_0":"up_arrow"}},"display":"arrowtriangle.up.fill"},"id":"B96FD0C2-6B0D-4D8A-8C95-BBA86408D1BC","toDetailCollection":{},"keyShape":"arrow_Up"},"row5":[],"idsInOrderRow4":[{"id":"DD644FC4-F6E6-42E4-B774-26AA8FBDC786"}],"arrow_left":{"keyShape":"arrow_LR","id":"5DD660A9-EC50-47E3-9892-DCBD1080EA39","toDetailCollection":{},"fromDetail":{"output":{"arrow_keys":{"_0":"left_arrow"}},"display":"arrowtriangle.left.fill","isSFSymbol":true}},"rowIndex_arrow":{"row6":{}},"arrow_down":{"fromDetail":{"output":{"arrow_keys":{"_0":"down_arrow"}},"isSFSymbol":true,"display":"arrowtriangle.down.fill"},"keyShape":"arrow_Down","toDetailCollection":{},"id":"056D7C10-A1C9-49C3-B47D-CFA3F854BFBD"},"idsInOrderRow3":[{"id":"9810826E-51FE-4B30-B957-5446CA40F15E"}]},"sectionDetail":{"deviceDetail":{"is_vendor_id_Enabled":false,"product_id":"product_id","location_id":"location_id","vendor_id":"vendor_id","is_builtin_keyboard":false,"is_location_id_Enabled":false,"device_name":"mouse","is_product_id_Enabled":false},"section":{"mouse":{}}},"isEnableMain":true,"isEnableSub":false},"keycodeRegion":"JIS","other":{"subRows":{"row6":[{"id":"916732DC-3DE1-46BC-99E6-2BC6C0C69D99","fromDetail":{"output":{"arrow_keys":{"_0":"down_arrow"}},"display":"arrowtriangle.down.fill","isSFSymbol":true},"toDetailCollection":{}},{"toDetailCollection":{},"id":"6F01C2D9-A9AE-40EE-9A1E-CD8DB6619C9B","fromDetail":{"display":"arrowtriangle.left.fill","isSFSymbol":true,"output":{"arrow_keys":{"_0":"left_arrow"}}}},{"toDetailCollection":{},"fromDetail":{"isSFSymbol":true,"output":{"arrow_keys":{"_0":"right_arrow"}},"display":"arrowtriangle.right.fill"},"id":"DEF610D5-1E6F-484D-B45C-FA34BF83C37C"}],"arrow_up":{"id":"1178BDBC-2EED-4DE4-A6D4-1AF10E0018CA","keyShape":"arrow_Up","fromDetail":{"output":{"arrow_keys":{"_0":"up_arrow"}},"isSFSymbol":true,"display":"arrowtriangle.up.fill"},"toDetailCollection":{}},"rowIndex_arrow":{"row6":{}},"idsInOrderRow3":[{"id":"E79A8AD8-5293-4BDB-907D-1300838A794E"},{"id":"6064F17D-A595-495D-92BF-D2407D4E2CF1"},{"id":"5C418B9C-502A-46F0-ACF4-37C7F24C11F8"}],"idsInOrderRow5":[{"id":"7CC435C0-04D3-4C0D-AB63-E3F0B5B8D593"},{"id":"92A88914-BE80-4456-8E5B-3FC9313A1D5D"}],"arrow_right":{"keyShape":"arrow_LR","id":"A9D17FF9-A7A4-4346-9946-5AFEE7A644EA","fromDetail":{"output":{"arrow_keys":{"_0":"right_arrow"}},"isSFSymbol":true,"display":"arrowtriangle.right.fill"},"toDetailCollection":{}},"row4":[],"idsInOrderRow1":[{"id":"A4623D42-AAA8-4500-9AC4-E5374B925F34"},{"id":"459391F0-9518-4F70-BBD8-BECE77D331BF"},{"id":"79A8F446-6F95-426D-8D8F-786695AE8594"}],"row2":[{"toDetailCollection":{},"id":"84205C49-B7DD-4303-9F1A-9E3DFACDC656","fromDetail":{"output":{"arrow_keys":{"_0":"home"}},"isSFSymbol":true,"display":"arrow.up.to.line"}},{"fromDetail":{"output":{"keys_in_pc_keyboards":{"_0":"insert"}},"display":"text.insert","isSFSymbol":true},"id":"29A38342-AD80-44E2-863B-AEE5277630F5","toDetailCollection":{}},{"toDetailCollection":{},"id":"7BAD99AD-BD2C-43B9-9948-35872AF9E340","fromDetail":{"output":{"arrow_keys":{"_0":"page_up"}},"isSFSymbol":true,"display":"arrow.up"}}],"row3":[{"fromDetail":{"output":{"arrow_keys":{"_0":"page_down"}},"isSFSymbol":true,"display":"arrow.down"},"id":"5C418B9C-502A-46F0-ACF4-37C7F24C11F8","toDetailCollection":{}},{"id":"6064F17D-A595-495D-92BF-D2407D4E2CF1","toDetailCollection":{},"fromDetail":{"display":"arrow.down.to.line","isSFSymbol":true,"output":{"arrow_keys":{"_0":"end"}}}},{"toDetailCollection":{},"id":"E79A8AD8-5293-4BDB-907D-1300838A794E","fromDetail":{"output":{"controls_and_symbols":{"_0":"delete_forward"}},"isSFSymbol":true,"display":"delete.right"}}],"arrow_down":{"keyShape":"arrow_Down","fromDetail":{"output":{"arrow_keys":{"_0":"down_arrow"}},"isSFSymbol":true,"display":"arrowtriangle.down.fill"},"id":"9F8D3EC7-9464-498D-AF12-76EFBE70760F","toDetailCollection":{}},"arrow_left":{"keyShape":"arrow_LR","id":"F68F658F-D294-4FA4-BD3A-9161CC6398CA","toDetailCollection":{},"fromDetail":{"output":{"arrow_keys":{"_0":"left_arrow"}},"display":"arrowtriangle.left.fill","isSFSymbol":true}},"idsInOrderRow4":[],"idsInOrderRow2":[{"id":"29A38342-AD80-44E2-863B-AEE5277630F5"},{"id":"84205C49-B7DD-4303-9F1A-9E3DFACDC656"},{"id":"7BAD99AD-BD2C-43B9-9948-35872AF9E340"}],"enableArrowKeys":false,"idsInOrderRow6":[{"id":"6F01C2D9-A9AE-40EE-9A1E-CD8DB6619C9B"},{"id":"916732DC-3DE1-46BC-99E6-2BC6C0C69D99"},{"id":"DEF610D5-1E6F-484D-B45C-FA34BF83C37C"}],"row1":[{"fromDetail":{"output":{"function_keys":{"_0":"f15"}},"display":"F15"},"id":"79A8F446-6F95-426D-8D8F-786695AE8594","toDetailCollection":{}},{"fromDetail":{"display":"F14","output":{"function_keys":{"_0":"f14"}}},"toDetailCollection":{},"id":"459391F0-9518-4F70-BBD8-BECE77D331BF"},{"fromDetail":{"display":"F13","output":{"function_keys":{"_0":"f13"}}},"toDetailCollection":{},"id":"A4623D42-AAA8-4500-9AC4-E5374B925F34"}],"row5":[{"id":"92A88914-BE80-4456-8E5B-3FC9313A1D5D","fromDetail":{"display":"arrowtriangle.up.fill","isSFSymbol":true,"output":{"arrow_keys":{"_0":"up_arrow"}}},"toDetailCollection":{}},{"fromDetail":{"output":{"letter_keys":{"_0":"a"}},"display":"A"},"toDetailCollection":{},"id":"7CC435C0-04D3-4C0D-AB63-E3F0B5B8D593","isSpacer":true}]},"mainRows":{"arrow_left":{"id":"6CDBD517-54D5-4CBB-9F8D-03F30E5A63A2","fromDetail":{"isSFSymbol":true,"output":{"arrow_keys":{"_0":"left_arrow"}},"display":"arrowtriangle.left.fill"},"keyShape":"arrow_LR","toDetailCollection":{}},"rowIndex_arrow":{"row6":{}},"arrow_up":{"fromDetail":{"output":{"arrow_keys":{"_0":"up_arrow"}},"display":"arrowtriangle.up.fill","isSFSymbol":true},"keyShape":"arrow_Up","toDetailCollection":{},"id":"03659BBB-9FED-4840-8AAC-55A41818012C"},"enableArrowKeys":false,"row3":[{"fromDetail":{"output":{"keypad_keys":{"_0":"keypad_8"}},"display":"8"},"toDetailCollection":{},"id":"3F6899B6-5395-4A10-B722-B284D39579A3"},{"fromDetail":{"display":"-","output":{"keypad_keys":{"_0":"keypad_hyphen"}}},"id":"B6F6171C-3E55-4E4E-81DB-472EC17ED500","toDetailCollection":{}},{"fromDetail":{"display":"9","output":{"keypad_keys":{"_0":"keypad_9"}}},"id":"6063C525-1DA7-43D7-B193-CB80171877F7","toDetailCollection":{}},{"fromDetail":{"display":"7","output":{"keypad_keys":{"_0":"keypad_7"}}},"id":"9CF44737-F347-4F58-904C-03B2255C22C0","toDetailCollection":{}}],"row4":[{"id":"AB21186F-8BAD-4636-BBAD-075C28D22CB7","fromDetail":{"output":{"keypad_keys":{"_0":"keypad_4"}},"display":"4"},"toDetailCollection":{}},{"id":"E85A4A15-FD8B-43E5-B7D0-0D33B0632AB7","fromDetail":{"display":"+","output":{"keypad_keys":{"_0":"keypad_plus"}}},"toDetailCollection":{}},{"id":"E9EF4B91-A3E2-4E2B-AB05-808D62FD572F","fromDetail":{"display":"6","output":{"keypad_keys":{"_0":"keypad_6"}}},"toDetailCollection":{}},{"id":"237F6153-6F38-41EF-A8CA-86ED426C803A","fromDetail":{"output":{"keypad_keys":{"_0":"keypad_5"}},"display":"5"},"toDetailCollection":{}}],"arrow_down":{"fromDetail":{"output":{"arrow_keys":{"_0":"down_arrow"}},"display":"arrowtriangle.down.fill","isSFSymbol":true},"toDetailCollection":{},"keyShape":"arrow_Down","id":"1B69DBC1-DF14-4201-B9D1-556C0C2988C3"},"arrow_right":{"keyShape":"arrow_LR","fromDetail":{"display":"arrowtriangle.right.fill","output":{"arrow_keys":{"_0":"right_arrow"}},"isSFSymbol":true},"id":"6D622950-397C-4C76-904A-7340AA448D5D","toDetailCollection":{}},"row5":[{"fromDetail":{"output":{"keypad_keys":{"_0":"keypad_1"}},"display":"1"},"toDetailCollection":{},"id":"2B098D56-9BA0-4D8E-B947-0629A24C71CE"},{"toDetailCollection":{},"fromDetail":{"display":"projective","output":{"keypad_keys":{"_0":"keypad_enter"}},"isSFSymbol":true},"keyShape":"enter_Tenkey","id":"00F3D327-13FE-45DB-B98C-99FAC9B21550"},{"id":"8C7E2CD9-BCC7-48BE-AD36-63A84D38B014","fromDetail":{"display":"3","output":{"keypad_keys":{"_0":"keypad_3"}}},"toDetailCollection":{}},{"id":"CCC754E6-9182-40E5-B419-11A66971B54F","toDetailCollection":{},"fromDetail":{"display":"2","output":{"keypad_keys":{"_0":"keypad_2"}}}}],"idsInOrderRow4":[{"id":"AB21186F-8BAD-4636-BBAD-075C28D22CB7"},{"id":"237F6153-6F38-41EF-A8CA-86ED426C803A"},{"id":"E9EF4B91-A3E2-4E2B-AB05-808D62FD572F"},{"id":"E85A4A15-FD8B-43E5-B7D0-0D33B0632AB7"}],"idsInOrderRow5":[{"id":"2B098D56-9BA0-4D8E-B947-0629A24C71CE"},{"id":"CCC754E6-9182-40E5-B419-11A66971B54F"},{"id":"8C7E2CD9-BCC7-48BE-AD36-63A84D38B014"},{"id":"00F3D327-13FE-45DB-B98C-99FAC9B21550"}],"row2":[{"id":"951D5DA3-6F0D-4B78-9F8C-12E628E91FED","fromDetail":{"display":"\/","output":{"keypad_keys":{"_0":"keypad_slash"}}},"toDetailCollection":{}},{"id":"FF41D734-8252-470C-BB9F-ACD7091953D4","fromDetail":{"output":{"keypad_keys":{"_0":"keypad_asterisk"}},"display":"*"},"toDetailCollection":{}},{"id":"92ED0E5D-C9C9-4EEE-A90A-F1259C71DB58","fromDetail":{"display":"clear","output":{"others":{"_0":"clear"}}},"toDetailCollection":{}},{"fromDetail":{"output":{"keypad_keys":{"_0":"keypad_equal_sign"}},"display":"="},"toDetailCollection":{},"id":"ACC09CF8-9677-444F-8234-971CE985A672"}],"idsInOrderRow2":[{"id":"92ED0E5D-C9C9-4EEE-A90A-F1259C71DB58"},{"id":"ACC09CF8-9677-444F-8234-971CE985A672"},{"id":"951D5DA3-6F0D-4B78-9F8C-12E628E91FED"},{"id":"FF41D734-8252-470C-BB9F-ACD7091953D4"}],"idsInOrderRow6":[{"id":"36A8682F-3786-4039-93E4-1F53F1F04FC8"},{"id":"F5C6FB39-E24F-4568-BA0F-6D5D48AD3A9C"},{"id":"4803DDD8-0954-48AA-8C2F-DEED0F9B2649"}],"idsInOrderRow3":[{"id":"9CF44737-F347-4F58-904C-03B2255C22C0"},{"id":"3F6899B6-5395-4A10-B722-B284D39579A3"},{"id":"6063C525-1DA7-43D7-B193-CB80171877F7"},{"id":"B6F6171C-3E55-4E4E-81DB-472EC17ED500"}],"row1":[{"id":"7B7816A3-84DB-41C9-8821-CC0F13A31492","fromDetail":{"output":{"function_keys":{"_0":"f18"}},"display":"F18"},"toDetailCollection":{}},{"id":"99207FAF-ABFE-419C-A7E2-6FA8100BF472","toDetailCollection":{},"fromDetail":{"output":{"function_keys":{"_0":"f19"}},"display":"F19"}},{"toDetailCollection":{},"id":"C6D61D82-11E8-4944-B6CE-2D319DF29CF3","fromDetail":{"output":{"function_keys":{"_0":"f17"}},"display":"F17"}},{"toDetailCollection":{},"id":"379F35A7-D034-4B94-9ABB-2D3CCCB2D83F","fromDetail":{"output":{"function_keys":{"_0":"f16"}},"display":"F16"}}],"idsInOrderRow1":[{"id":"379F35A7-D034-4B94-9ABB-2D3CCCB2D83F"},{"id":"C6D61D82-11E8-4944-B6CE-2D319DF29CF3"},{"id":"7B7816A3-84DB-41C9-8821-CC0F13A31492"},{"id":"99207FAF-ABFE-419C-A7E2-6FA8100BF472"}],"row6":[{"toDetailCollection":{},"fromDetail":{"output":{"keypad_keys":{"_0":"keypad_period"}},"display":"."},"id":"4803DDD8-0954-48AA-8C2F-DEED0F9B2649"},{"fromDetail":{"display":",","output":{"keypad_keys":{"_0":"keypad_comma"}}},"toDetailCollection":{},"id":"F5C6FB39-E24F-4568-BA0F-6D5D48AD3A9C"},{"fromDetail":{"output":{"keypad_keys":{"_0":"keypad_0"}},"display":"0"},"id":"36A8682F-3786-4039-93E4-1F53F1F04FC8","toDetailCollection":{}}]},"isEnableMain":true,"isEnableSub":false,"sectionDetail":{"section":{"other":{}},"deviceDetail":{"device_name":"otherDevice","product_id":"product_id","is_builtin_keyboard":false,"is_product_id_Enabled":false,"is_location_id_Enabled":false,"is_vendor_id_Enabled":false,"vendor_id":"vendor_id","location_id":"location_id"}},"tenkeyRows":{"row4":[{"fromDetail":{"display":"4","output":{"keypad_keys":{"_0":"keypad_4"}}},"toDetailCollection":{},"id":"25F96B35-9BFC-4D27-93E7-04F7D8A6EF50"},{"id":"7EAE83F5-44E6-40D6-8446-BD068447B58D","fromDetail":{"display":"+","output":{"keypad_keys":{"_0":"keypad_plus"}}},"toDetailCollection":{}},{"toDetailCollection":{},"id":"5F4A1DBF-4ECE-4BE7-976F-A4E24F6FB07F","fromDetail":{"display":"5","output":{"keypad_keys":{"_0":"keypad_5"}}}},{"id":"9802375D-EECD-4A5B-B012-86703A7B419D","fromDetail":{"output":{"keypad_keys":{"_0":"keypad_6"}},"display":"6"},"toDetailCollection":{}}],"enableArrowKeys":false,"row3":[{"toDetailCollection":{},"id":"A668B2C8-32BD-49AB-B4A1-E40F704EEDE1","fromDetail":{"display":"8","output":{"keypad_keys":{"_0":"keypad_8"}}}},{"id":"DD209E86-FD04-4CF1-8F4E-E718A29A2328","fromDetail":{"output":{"keypad_keys":{"_0":"keypad_9"}},"display":"9"},"toDetailCollection":{}},{"id":"51EC0D71-39CE-4512-A297-0F6A28929E94","toDetailCollection":{},"fromDetail":{"display":"-","output":{"keypad_keys":{"_0":"keypad_hyphen"}}}},{"fromDetail":{"output":{"keypad_keys":{"_0":"keypad_7"}},"display":"7"},"toDetailCollection":{},"id":"974E90BF-6D7E-4040-8BEA-2233EFC540F7"}],"idsInOrderRow4":[{"id":"25F96B35-9BFC-4D27-93E7-04F7D8A6EF50"},{"id":"5F4A1DBF-4ECE-4BE7-976F-A4E24F6FB07F"},{"id":"9802375D-EECD-4A5B-B012-86703A7B419D"},{"id":"7EAE83F5-44E6-40D6-8446-BD068447B58D"}],"rowIndex_arrow":{"row6":{}},"row5":[{"fromDetail":{"display":"2","output":{"keypad_keys":{"_0":"keypad_2"}}},"id":"ED2BDD0C-B937-473D-B6D4-709655EF2C68","toDetailCollection":{}},{"id":"679F2392-2E92-4F26-A277-59B06F78B5AC","fromDetail":{"display":"3","output":{"keypad_keys":{"_0":"keypad_3"}}},"toDetailCollection":{}},{"fromDetail":{"isSFSymbol":true,"output":{"keypad_keys":{"_0":"keypad_enter"}},"display":"projective"},"toDetailCollection":{},"id":"1F23A086-B883-442D-AA34-4A134AC64341","keyShape":"enter_Tenkey"},{"id":"C6BA1391-7DC7-4CF0-BA1B-131BBCC73E27","fromDetail":{"output":{"keypad_keys":{"_0":"keypad_1"}},"display":"1"},"toDetailCollection":{}}],"idsInOrderRow3":[{"id":"974E90BF-6D7E-4040-8BEA-2233EFC540F7"},{"id":"A668B2C8-32BD-49AB-B4A1-E40F704EEDE1"},{"id":"DD209E86-FD04-4CF1-8F4E-E718A29A2328"},{"id":"51EC0D71-39CE-4512-A297-0F6A28929E94"}],"arrow_up":{"fromDetail":{"isSFSymbol":true,"output":{"arrow_keys":{"_0":"up_arrow"}},"display":"arrowtriangle.up.fill"},"toDetailCollection":{},"id":"5BE4FA3D-8556-443C-BDE8-AF0064C832F6","keyShape":"arrow_Up"},"idsInOrderRow2":[{"id":"A0A2CAD4-3DD0-4BC7-B9F7-ABE635816268"},{"id":"41D9D5EB-A396-44D7-8154-61D0C46AE6FF"},{"id":"42BE8D66-DD02-49E2-8B16-89B07A4A9196"},{"id":"C094AF25-24A6-42C3-9CC5-DE53DCCE9285"}],"row1":[{"id":"F2CC4EDE-ECD5-46FC-8D4C-281CA0B88902","fromDetail":{"display":"F18","output":{"function_keys":{"_0":"f18"}}},"toDetailCollection":{}},{"fromDetail":{"output":{"function_keys":{"_0":"f17"}},"display":"F17"},"id":"D5056528-6D6F-4164-AC08-2E8A01D429A0","toDetailCollection":{}},{"id":"4567DFE4-7A92-4BE7-B5D2-5170A926B79F","toDetailCollection":{},"fromDetail":{"output":{"function_keys":{"_0":"f16"}},"display":"F16"}},{"fromDetail":{"output":{"function_keys":{"_0":"f19"}},"display":"F19"},"id":"A48F4D3A-A850-472F-AB03-72D9BBE11911","toDetailCollection":{}}],"arrow_right":{"id":"4035A1C6-619E-4E95-AB0A-79D5080F31FF","keyShape":"arrow_LR","toDetailCollection":{},"fromDetail":{"display":"arrowtriangle.right.fill","isSFSymbol":true,"output":{"arrow_keys":{"_0":"right_arrow"}}}},"arrow_left":{"keyShape":"arrow_LR","fromDetail":{"output":{"arrow_keys":{"_0":"left_arrow"}},"isSFSymbol":true,"display":"arrowtriangle.left.fill"},"toDetailCollection":{},"id":"7B6159E9-6403-42C2-A53B-8052CC2449F7"},"row2":[{"fromDetail":{"display":"*","output":{"keypad_keys":{"_0":"keypad_asterisk"}}},"toDetailCollection":{},"id":"C094AF25-24A6-42C3-9CC5-DE53DCCE9285"},{"toDetailCollection":{},"id":"41D9D5EB-A396-44D7-8154-61D0C46AE6FF","fromDetail":{"display":"=","output":{"keypad_keys":{"_0":"keypad_equal_sign"}}}},{"toDetailCollection":{},"id":"A0A2CAD4-3DD0-4BC7-B9F7-ABE635816268","fromDetail":{"display":"clear","output":{"others":{"_0":"clear"}}}},{"fromDetail":{"output":{"keypad_keys":{"_0":"keypad_slash"}},"display":"\/"},"id":"42BE8D66-DD02-49E2-8B16-89B07A4A9196","toDetailCollection":{}}],"idsInOrderRow1":[{"id":"4567DFE4-7A92-4BE7-B5D2-5170A926B79F"},{"id":"D5056528-6D6F-4164-AC08-2E8A01D429A0"},{"id":"F2CC4EDE-ECD5-46FC-8D4C-281CA0B88902"},{"id":"A48F4D3A-A850-472F-AB03-72D9BBE11911"}],"idsInOrderRow5":[{"id":"C6BA1391-7DC7-4CF0-BA1B-131BBCC73E27"},{"id":"ED2BDD0C-B937-473D-B6D4-709655EF2C68"},{"id":"679F2392-2E92-4F26-A277-59B06F78B5AC"},{"id":"1F23A086-B883-442D-AA34-4A134AC64341"}],"idsInOrderRow6":[{"id":"8FC06134-EA6E-46C7-96D7-93E193CBB0E8"},{"id":"C4F70A23-CB77-4C4F-A1A5-B5A9B411E256"},{"id":"A2EDFBF6-FA88-4CC8-BE80-C594DE7FCD52"}],"row6":[{"fromDetail":{"output":{"keypad_keys":{"_0":"keypad_period"}},"display":"."},"toDetailCollection":{},"id":"A2EDFBF6-FA88-4CC8-BE80-C594DE7FCD52"},{"fromDetail":{"display":"0","output":{"keypad_keys":{"_0":"keypad_0"}}},"toDetailCollection":{},"id":"8FC06134-EA6E-46C7-96D7-93E193CBB0E8"},{"fromDetail":{"output":{"keypad_keys":{"_0":"keypad_comma"}},"display":","},"toDetailCollection":{},"id":"C4F70A23-CB77-4C4F-A1A5-B5A9B411E256"}],"arrow_down":{"keyShape":"arrow_Down","fromDetail":{"isSFSymbol":true,"output":{"arrow_keys":{"_0":"down_arrow"}},"display":"arrowtriangle.down.fill"},"id":"B77FF93F-B56C-4625-96DB-A4C538DF80D6","toDetailCollection":{}}},"isEnableTenkey":false}},"comboCollection":{"condition6":{"layer4":{},"layer2":{},"layer1":{},"layer6":{},"layer7":{},"layer8":{},"layer0":{},"layer5":{},"layer3":{}},"condition2":{"layer4":{},"layer2":{},"layer5":{},"layer0":{},"layer6":{},"layer1":{},"layer8":{},"layer7":{},"layer3":{}},"condition4":{"layer2":{},"layer1":{},"layer8":{},"layer5":{},"layer0":{},"layer6":{},"layer7":{},"layer3":{},"layer4":{}},"condition8":{"layer3":{},"layer0":{},"layer4":{},"layer5":{},"layer7":{},"layer8":{},"layer1":{},"layer6":{},"layer2":{}},"condition0":{"layer0":{},"layer7":{},"layer8":{},"layer3":{},"layer6":{},"layer1":{},"layer2":{},"layer5":{},"layer4":{}},"condition9":{"layer8":{},"layer2":{},"layer7":{},"layer0":{},"layer3":{},"layer6":{},"layer4":{},"layer5":{},"layer1":{}},"condition5":{"layer6":{},"layer5":{},"layer2":{},"layer3":{},"layer1":{},"layer7":{},"layer8":{},"layer4":{},"layer0":{}},"condition1":{"layer4":{},"layer7":{},"layer3":{},"layer1":{},"layer2":{},"layer5":{},"layer6":{},"layer8":{},"layer0":{}},"condition7":{"layer4":{},"layer5":{},"layer8":{},"layer2":{},"layer3":{},"layer1":{},"layer0":{},"layer6":{},"layer7":{}},"condition3":{"layer3":{},"layer7":{},"layer6":{},"layer1":{},"layer4":{},"layer5":{},"layer0":{},"layer2":{},"layer8":{}}},"displayKeySize":65,"conditionDetailCollection":{"condition7":{"name":"Condition7","value":"com.vendor.condition7","type":"Application","isEnabled":false},"condition4":{"name":"Condition4","isEnabled":false,"value":"com.vendor.condition4","type":"Application"},"condition8":{"type":"Application","name":"Condition8","isEnabled":false,"value":"com.vendor.condition8"},"condition9":{"name":"Condition9","value":"com.vendor.condition9","type":"Application","isEnabled":false},"condition0":{"name":"Default","isEnabled":true,"type":"Application","value":"com.vendor.condition0"},"condition3":{"name":"Condition3","type":"Application","value":"com.vendor.condition3","isEnabled":false},"condition5":{"type":"Application","name":"Condition5","value":"com.vendor.condition5","isEnabled":false},"condition6":{"value":"com.vendor.condition6","type":"Application","name":"Condition6","isEnabled":false},"condition2":{"value":"com.vendor.condition2","isEnabled":false,"type":"Application","name":"Condition2"},"condition1":{"name":"Condition1","isEnabled":false,"value":"ja","type":"InputSource"}}}